pydantic_alchemy/__init__.py
pydantic_alchemy-0.1.2.dist-info/METADATA
pydantic_alchemy-0.1.2.dist-info/WHEEL
pydantic_alchemy-0.1.2.dist-info/licenses/LICENSE
pydantic_alchemy-0.1.2.dist-info/RECORD
