Metadata-Version: 2.4
Name: pydantic-alchemy
Version: 0.1.2
Summary: A library to seamlessly integrate SQLAlchemy models with Pydantic. Useful for building fast, type-safe APIs and data pipelines.
Project-URL: homepage, https://github.com/eyueldk/pydantic-alchemy
Project-URL: repository, https://github.com/eyueldk/pydantic-alchemy
Author: eyueldk
License: MIT
License-File: LICENSE
Keywords: api,data validation,models,orm,pydantic,sqlalchemy
Classifier: Intended Audience :: Developers
Classifier: License :: OSI Approved :: MIT License
Classifier: Operating System :: OS Independent
Classifier: Programming Language :: Python :: 3
Classifier: Topic :: Software Development :: Libraries :: Python Modules
Requires-Python: >=3.9
Requires-Dist: sqlalchemy>=2.0.0
